{"volcano_json": {"type": "FeatureCollection", "features": [{"geometry": {"type": "Point", "coordinates": [-78.442, -1.467]}, "type": "Feature", "id": 0, "properties": {"Houses_Destroyed": "", "Elevation": 5023, "Name": "Tungurahua", "Deaths": "", "Country": "Ecuador", "Missing": "", "Longitude": -78.442, "Month": 1, "Injuries": "", "Location": "Ecuador", "Volcano Type": "Stratovolcano", "Year": 2010, "Latitude": -1.467, "Type": "Volcanic Activity", "Day": "", "Damage_Millions_Dollars": "", "VEI": 3}}, {"geometry": {"type": "Point", "coordinates": [-19.62, 63.63]}, "type": "Feature", "id": 1, "properties": {"Houses_Destroyed": "", "Elevation": 1666, "Name": "Eyjafjallajokull", "Deaths": 2, "Country": "Iceland", "Missing": "", "Longitude": -19.62, "Month": 3, "Injuries": "", "Location": "Iceland-S", "Volcano Type": "Stratovolcano", "Year": 2010, "Latitude": 63.63, "Type": "Volcanic Activity", "Day": 31, "Damage_Millions_Dollars": "", "VEI": 2}}, {"geometry": {"type": "Point", "coordinates": [-90.601, 14.381]}, "type": "Feature", "id": 2, "properties": {"Houses_Destroyed": 3, "Elevation": 2552, "Name": "Pacaya", "Deaths": 1, "Country": "Guatemala", "Missing": 3, "Longitude": -90.601, "Month": 5, "Injuries": "", "Location": "Guatemala", "Volcano Type": "Complex volcano", "Year": 2010, "Latitude": 14.381, "Type": "Volcanic Activity", "Day": 27, "Damage_Millions_Dollars": "", "VEI": 1}}, {"geometry": {"type": "Point", "coordinates": [145.78, 16.708]}, "type": "Feature", "id": 3, "properties": {"Houses_Destroyed": "", "Elevation": 538, "Name": "Sarigan", "Deaths": "", "Country": "United States", "Missing": "", "Longitude": 145.78, "Month": 5, "Injuries": "", "Location": "Mariana Is-C Pacific", "Volcano Type": "Stratovolcano", "Year": 2010, "Latitude": 16.708, "Type": "Volcanic Activity", "Day": 29, "Damage_Millions_Dollars": "", "VEI": ""}}, {"geometry": {"type": "Point", "coordinates": [125.48, 2.78]}, "type": "Feature", "id": 4, "properties": {"Houses_Destroyed": "", "Elevation": 1784, "Name": "Karangetang [Api Siau]", "Deaths": 4, "Country": "Indonesia", "Missing": "", "Longitude": 125.48, "Month": 8, "Injuries": 5, "Location": "Sangihe Is-Indonesia", "Volcano Type": "Stratovolcano", "Year": 2010, "Latitude": 2.78, "Type": "Volcanic Activity", "Day": 6, "Damage_Millions_Dollars": "", "VEI": 3}}, {"geometry": {"type": "Point", "coordinates": [98.392, 3.17]}, "type": "Feature", "id": 5, "properties": {"Houses_Destroyed": "", "Elevation": 2460, "Name": "Sinabung", "Deaths": 2, "Country": "Indonesia", "Missing": "", "Longitude": 98.392, "Month": 8, "Injuries": "", "Location": "Sumatra", "Volcano Type": "Stratovolcano", "Year": 2010, "Latitude": 3.17, "Type": "Volcanic Activity", "Day": 30, "Damage_Millions_Dollars": "", "VEI": ""}}, {"geometry": {"type": "Point", "coordinates": [110.442, -7.542]}, "type": "Feature", "id": 6, "properties": {"Houses_Destroyed": "", "Elevation": 2947, "Name": "Merapi", "Deaths": 367, "Country": "Indonesia", "Missing": "", "Longitude": 110.442, "Month": 10, "Injuries": 277, "Location": "Java", "Volcano Type": "Stratovolcano", "Year": 2010, "Latitude": -7.542, "Type": "Volcanic Activity", "Day": 26, "Damage_Millions_Dollars": 600, "VEI": ""}}, {"geometry": {"type": "Point", "coordinates": [-78.442, -1.467]}, "type": "Feature", "id": 7, "properties": {"Houses_Destroyed": "", "Elevation": 5023, "Name": "Tungurahua", "Deaths": "", "Country": "Ecuador", "Missing": "", "Longitude": -78.442, "Month": 11, "Injuries": "", "Location": "Ecuador", "Volcano Type": "Stratovolcano", "Year": 2010, "Latitude": -1.467, "Type": "Volcanic Activity", "Day": "", "Damage_Millions_Dollars": "", "VEI": 3}}, {"geometry": {"type": "Point", "coordinates": [112.95, -7.942]}, "type": "Feature", "id": 8, "properties": {"Houses_Destroyed": "", "Elevation": 2329, "Name": "Tengger Caldera", "Deaths": "", "Country": "Indonesia", "Missing": "", "Longitude": 112.95, "Month": 12, "Injuries": "", "Location": "Java", "Volcano Type": "Stratovolcano", "Year": 2010, "Latitude": -7.942, "Type": "Volcanic Activity", "Day": 28, "Damage_Millions_Dollars": "", "VEI": ""}}, {"geometry": {"type": "Point", "coordinates": [110.442, -7.542]}, "type": "Feature", "id": 9, "properties": {"Houses_Destroyed": "", "Elevation": 2947, "Name": "Merapi", "Deaths": 1, "Country": "Indonesia", "Missing": "", "Longitude": 110.442, "Month": 1, "Injuries": 1, "Location": "Java", "Volcano Type": "Stratovolcano", "Year": 2011, "Latitude": -7.542, "Type": "Volcanic Activity", "Day": 3, "Damage_Millions_Dollars": "", "VEI": ""}}, {"geometry": {"type": "Point", "coordinates": [130.87, 31.93]}, "type": "Feature", "id": 10, "properties": {"Houses_Destroyed": "", "Elevation": 1700, "Name": "Kirishima", "Deaths": "", "Country": "Japan", "Missing": "", "Longitude": 130.87, "Month": 1, "Injuries": "", "Location": "Kyushu-Japan", "Volcano Type": "Shield volcano", "Year": 2011, "Latitude": 31.93, "Type": "Volcanic Activity", "Day": 28, "Damage_Millions_Dollars": "", "VEI": ""}}, {"geometry": {"type": "Point", "coordinates": [124.05, 12.77]}, "type": "Feature", "id": 11, "properties": {"Houses_Destroyed": "", "Elevation": 1565, "Name": "Bulusan", "Deaths": 1, "Country": "Philippines", "Missing": "", "Longitude": 124.05, "Month": 2, "Injuries": "", "Location": "Luzon-Philippines", "Volcano Type": "Stratovolcano", "Year": 2011, "Latitude": 12.77, "Type": "Volcanic Activity", "Day": 23, "Damage_Millions_Dollars": "", "VEI": 2}}, {"geometry": {"type": "Point", "coordinates": [125.48, 2.78]}, "type": "Feature", "id": 12, "properties": {"Houses_Destroyed": "", "Elevation": 1784, "Name": "Karangetang [Api Siau]", "Deaths": "", "Country": "Indonesia", "Missing": "", "Longitude": 125.48, "Month": 3, "Injuries": "", "Location": "Sangihe Is-Indonesia", "Volcano Type": "Stratovolcano", "Year": 2011, "Latitude": 2.78, "Type": "Volcanic Activity", "Day": 18, "Damage_Millions_Dollars": "", "VEI": ""}}, {"geometry": {"type": "Point", "coordinates": [-78.442, -1.467]}, "type": "Feature", "id": 13, "properties": {"Houses_Destroyed": "", "Elevation": 5023, "Name": "Tungurahua", "Deaths": "", "Country": "Ecuador", "Missing": "", "Longitude": -78.442, "Month": 4, "Injuries": "", "Location": "Ecuador", "Volcano Type": "Stratovolcano", "Year": 2011, "Latitude": -1.467, "Type": "Volcanic Activity", "Day": "", "Damage_Millions_Dollars": "", "VEI": 4}}, {"geometry": {"type": "Point", "coordinates": [-72.117, -40.59]}, "type": "Feature", "id": 14, "properties": {"Houses_Destroyed": "", "Elevation": 2236, "Name": "Puyehue", "Deaths": "", "Country": "Chile", "Missing": "", "Longitude": -72.117, "Month": 6, "Injuries": "", "Location": "Chile-C", "Volcano Type": "Stratovolcano", "Year": 2011, "Latitude": -40.59, "Type": "Volcanic Activity", "Day": 4, "Damage_Millions_Dollars": "", "VEI": 4}}, {"geometry": {"type": "Point", "coordinates": [41.7, 13.37]}, "type": "Feature", "id": 15, "properties": {"Houses_Destroyed": "", "Elevation": 2218, "Name": "Nabro", "Deaths": 31, "Country": "Eritrea", "Missing": "", "Longitude": 41.7, "Month": 6, "Injuries": "", "Location": "Africa-NE", "Volcano Type": "Stratovolcano", "Year": 2011, "Latitude": 13.37, "Type": "Volcanic Activity", "Day": 22, "Damage_Millions_Dollars": "", "VEI": 3}}, {"geometry": {"type": "Point", "coordinates": [-19.05, 63.63]}, "type": "Feature", "id": 16, "properties": {"Houses_Destroyed": "", "Elevation": 1512, "Name": "Katla", "Deaths": "", "Country": "Iceland", "Missing": "", "Longitude": -19.05, "Month": 7, "Injuries": "", "Location": "Iceland-S", "Volcano Type": "Subglacial volcano", "Year": 2011, "Latitude": 63.63, "Type": "Volcanic Activity", "Day": 9, "Damage_Millions_Dollars": "", "VEI": ""}}, {"geometry": {"type": "Point", "coordinates": [124.792, 1.358]}, "type": "Feature", "id": 17, "properties": {"Houses_Destroyed": "", "Elevation": 1580, "Name": "Lokon-Empung", "Deaths": 1, "Country": "Indonesia", "Missing": "", "Longitude": 124.792, "Month": 7, "Injuries": "", "Location": "Sulawesi-Indonesia", "Volcano Type": "Stratovolcano", "Year": 2011, "Latitude": 1.358, "Type": "Volcanic Activity", "Day": 17, "Damage_Millions_Dollars": "", "VEI": ""}}, {"geometry": {"type": "Point", "coordinates": [127.325, ".8"]}, "type": "Feature", "id": 18, "properties": {"Houses_Destroyed": "", "Elevation": 1715, "Name": "Gamalama", "Deaths": 4, "Country": "Indonesia", "Missing": "", "Longitude": 127.325, "Month": 12, "Injuries": "", "Location": "Halmahera-Indonesia", "Volcano Type": "Stratovolcano", "Year": 2011, "Latitude": ".8", "Type": "Volcanic Activity", "Day": 27, "Damage_Millions_Dollars": "", "VEI": 3}}, {"geometry": {"type": "Point", "coordinates": [-155.292, 19.425]}, "type": "Feature", "id": 19, "properties": {"Houses_Destroyed": "", "Elevation": 1222, "Name": "Kilauea", "Deaths": "", "Country": "United States", "Missing": "", "Longitude": -155.292, "Month": 2, "Injuries": "", "Location": "Hawaiian Is", "Volcano Type": "Shield volcano", "Year": 2012, "Latitude": 19.425, "Type": "Volcanic Activity", "Day": 10, "Damage_Millions_Dollars": "", "VEI": ""}}, {"geometry": {"type": "Point", "coordinates": [-155.292, 19.425]}, "type": "Feature", "id": 20, "properties": {"Houses_Destroyed": "", "Elevation": 1222, "Name": "Kilauea", "Deaths": "", "Country": "United States", "Missing": "", "Longitude": -155.292, "Month": 3, "Injuries": "", "Location": "Hawaiian Is", "Volcano Type": "Shield volcano", "Year": 2012, "Latitude": 19.425, "Type": "Volcanic Activity", "Day": 2, "Damage_Millions_Dollars": "", "VEI": ""}}, {"geometry": {"type": "Point", "coordinates": [160.33, 55.83]}, "type": "Feature", "id": 21, "properties": {"Houses_Destroyed": "", "Elevation": 3682, "Name": "Tolbachik", "Deaths": "", "Country": "Russia", "Missing": "", "Longitude": 160.33, "Month": 12, "Injuries": "", "Location": "Kamchatka", "Volcano Type": "Shield volcano", "Year": 2012, "Latitude": 55.83, "Type": "Volcanic Activity", "Day": 12, "Damage_Millions_Dollars": "", "VEI": ""}}, {"geometry": {"type": "Point", "coordinates": [110.442, -7.542]}, "type": "Feature", "id": 22, "properties": {"Houses_Destroyed": "", "Elevation": 2947, "Name": "Merapi", "Deaths": 1, "Country": "Indonesia", "Missing": "", "Longitude": 110.442, "Month": 2, "Injuries": 1, "Location": "Java", "Volcano Type": "Stratovolcano", "Year": 2013, "Latitude": -7.542, "Type": "Volcanic Activity", "Day": 12, "Damage_Millions_Dollars": "", "VEI": ""}}, {"geometry": {"type": "Point", "coordinates": [121.708, -8.32]}, "type": "Feature", "id": 23, "properties": {"Houses_Destroyed": "", "Elevation": 875, "Name": "Paluweh", "Deaths": "", "Country": "Indonesia", "Missing": "", "Longitude": 121.708, "Month": 2, "Injuries": "", "Location": "Lesser Sunda Is", "Volcano Type": "Stratovolcano", "Year": 2013, "Latitude": -8.32, "Type": "Volcanic Activity", "Day": "", "Damage_Millions_Dollars": "", "VEI": ""}}, {"geometry": {"type": "Point", "coordinates": [123.685, 13.257]}, "type": "Feature", "id": 24, "properties": {"Houses_Destroyed": "", "Elevation": 2462, "Name": "Mayon", "Deaths": 5, "Country": "Philippines", "Missing": "", "Longitude": 123.685, "Month": 5, "Injuries": 8, "Location": "Luzon-Philippines", "Volcano Type": "Stratovolcano", "Year": 2013, "Latitude": 13.257, "Type": "Volcanic Activity", "Day": 7, "Damage_Millions_Dollars": "", "VEI": ""}}, {"geometry": {"type": "Point", "coordinates": [121.708, -8.32]}, "type": "Feature", "id": 25, "properties": {"Houses_Destroyed": "", "Elevation": 875, "Name": "Paluweh", "Deaths": 5, "Country": "Indonesia", "Missing": "", "Longitude": 121.708, "Month": 8, "Injuries": "", "Location": "Lesser Sunda Is", "Volcano Type": "Stratovolcano", "Year": 2013, "Latitude": -8.32, "Type": "Volcanic Activity", "Day": 10, "Damage_Millions_Dollars": "", "VEI": 3}}, {"geometry": {"type": "Point", "coordinates": [-70.903, -16.355]}, "type": "Feature", "id": 26, "properties": {"Houses_Destroyed": "", "Elevation": 5672, "Name": "Ubinas", "Deaths": "", "Country": "Peru", "Missing": "", "Longitude": -70.903, "Month": 9, "Injuries": "", "Location": "Peru", "Volcano Type": "Stratovolcano", "Year": 2013, "Latitude": -16.355, "Type": "Volcanic Activity", "Day": 1, "Damage_Millions_Dollars": "", "VEI": ""}}, {"geometry": {"type": "Point", "coordinates": [130.67, 31.58]}, "type": "Feature", "id": 27, "properties": {"Houses_Destroyed": "", "Elevation": 1117, "Name": "Sakura-jima", "Deaths": "", "Country": "Japan", "Missing": "", "Longitude": 130.67, "Month": 9, "Injuries": "", "Location": "Kyushu-Japan", "Volcano Type": "Stratovolcano", "Year": 2013, "Latitude": 31.58, "Type": "Volcanic Activity", "Day": 4, "Damage_Millions_Dollars": "", "VEI": ""}}, {"geometry": {"type": "Point", "coordinates": [98.392, 3.17]}, "type": "Feature", "id": 28, "properties": {"Houses_Destroyed": "", "Elevation": 2460, "Name": "Sinabung", "Deaths": "", "Country": "Indonesia", "Missing": "", "Longitude": 98.392, "Month": 9, "Injuries": "", "Location": "Sumatra", "Volcano Type": "Stratovolcano", "Year": 2013, "Latitude": 3.17, "Type": "Volcanic Activity", "Day": 15, "Damage_Millions_Dollars": "", "VEI": 2}}, {"geometry": {"type": "Point", "coordinates": [176.5, -38.12]}, "type": "Feature", "id": 29, "properties": {"Houses_Destroyed": "", "Elevation": 1111, "Name": "Okataina", "Deaths": 1, "Country": "New Zealand", "Missing": "", "Longitude": 176.5, "Month": 12, "Injuries": "", "Location": "New Zealand", "Volcano Type": "Lava dome", "Year": 2013, "Latitude": -38.12, "Type": "Volcanic Activity", "Day": 13, "Damage_Millions_Dollars": "", "VEI": ""}}, {"geometry": {"type": "Point", "coordinates": [98.392, 3.17]}, "type": "Feature", "id": 30, "properties": {"Houses_Destroyed": "", "Elevation": 2460, "Name": "Sinabung", "Deaths": 17, "Country": "Indonesia", "Missing": "", "Longitude": 98.392, "Month": 2, "Injuries": 3, "Location": "Sumatra", "Volcano Type": "Stratovolcano", "Year": 2014, "Latitude": 3.17, "Type": "Volcanic Activity", "Day": 1, "Damage_Millions_Dollars": "", "VEI": ""}}, {"geometry": {"type": "Point", "coordinates": [112.308, -7.93]}, "type": "Feature", "id": 31, "properties": {"Houses_Destroyed": 4098, "Elevation": 1731, "Name": "Kelut", "Deaths": 7, "Country": "Indonesia", "Missing": "", "Longitude": 112.308, "Month": 2, "Injuries": "", "Location": "Java", "Volcano Type": "Stratovolcano", "Year": 2014, "Latitude": -7.93, "Type": "Volcanic Activity", "Day": 13, "Damage_Millions_Dollars": "", "VEI": ""}}, {"geometry": {"type": "Point", "coordinates": [137.48, 35.9]}, "type": "Feature", "id": 32, "properties": {"Houses_Destroyed": "", "Elevation": 3063, "Name": "On-take", "Deaths": 55, "Country": "Japan", "Missing": "", "Longitude": 137.48, "Month": 9, "Injuries": 70, "Location": "Honshu-Japan", "Volcano Type": "Complex volcano", "Year": 2014, "Latitude": 35.9, "Type": "Volcanic Activity", "Day": 27, "Damage_Millions_Dollars": "", "VEI": 3}}, {"geometry": {"type": "Point", "coordinates": [-155.292, 19.425]}, "type": "Feature", "id": 33, "properties": {"Houses_Destroyed": 1, "Elevation": 1222, "Name": "Kilauea", "Deaths": "", "Country": "United States", "Missing": "", "Longitude": -155.292, "Month": 11, "Injuries": "", "Location": "Hawaiian Is", "Volcano Type": "Shield volcano", "Year": 2014, "Latitude": 19.425, "Type": "Volcanic Activity", "Day": 10, "Damage_Millions_Dollars": 14.5, "VEI": ""}}, {"geometry": {"type": "Point", "coordinates": [-24.35, 14.95]}, "type": "Feature", "id": 34, "properties": {"Houses_Destroyed": 230, "Elevation": 2829, "Name": "Fogo", "Deaths": "", "Country": "Cape Verde", "Missing": "", "Longitude": -24.35, "Month": 11, "Injuries": "", "Location": "Cape Verde Is", "Volcano Type": "Stratovolcano", "Year": 2014, "Latitude": 14.95, "Type": "Volcanic Activity", "Day": 23, "Damage_Millions_Dollars": "", "VEI": ""}}, {"geometry": {"type": "Point", "coordinates": [127.325, ".8"]}, "type": "Feature", "id": 35, "properties": {"Houses_Destroyed": "", "Elevation": 1715, "Name": "Gamalama", "Deaths": 1, "Country": "Indonesia", "Missing": "", "Longitude": 127.325, "Month": 12, "Injuries": 4, "Location": "Halmahera-Indonesia", "Volcano Type": "Stratovolcano", "Year": 2014, "Latitude": ".8", "Type": "Volcanic Activity", "Day": 18, "Damage_Millions_Dollars": "", "VEI": ""}}, {"geometry": {"type": "Point", "coordinates": [98.392, 3.17]}, "type": "Feature", "id": 36, "properties": {"Houses_Destroyed": "", "Elevation": 2460, "Name": "Sinabung", "Deaths": "", "Country": "Indonesia", "Missing": "", "Longitude": 98.392, "Month": 2, "Injuries": "", "Location": "Sumatra", "Volcano Type": "Stratovolcano", "Year": 2015, "Latitude": 3.17, "Type": "Volcanic Activity", "Day": 20, "Damage_Millions_Dollars": "", "VEI": ""}}, {"geometry": {"type": "Point", "coordinates": [-72.614, -41.326]}, "type": "Feature", "id": 37, "properties": {"Houses_Destroyed": "", "Elevation": 2003, "Name": "Calbuco", "Deaths": "", "Country": "Chile", "Missing": "", "Longitude": -72.614, "Month": 4, "Injuries": "", "Location": "Chile-S", "Volcano Type": "Stratovolcano", "Year": 2015, "Latitude": -41.326, "Type": "Volcanic Activity", "Day": 22, "Damage_Millions_Dollars": "", "VEI": ""}}, {"geometry": {"type": "Point", "coordinates": [125.48, 2.78]}, "type": "Feature", "id": 38, "properties": {"Houses_Destroyed": "", "Elevation": 1784, "Name": "Karangetang [Api Siau]", "Deaths": "", "Country": "Indonesia", "Missing": "", "Longitude": 125.48, "Month": 5, "Injuries": "", "Location": "Sangihe Is-Indonesia", "Volcano Type": "Stratovolcano", "Year": 2015, "Latitude": 2.78, "Type": "Volcanic Activity", "Day": 7, "Damage_Millions_Dollars": "", "VEI": ""}}, {"geometry": {"type": "Point", "coordinates": [145.061, -4.1]}, "type": "Feature", "id": 39, "properties": {"Houses_Destroyed": "", "Elevation": 1807, "Name": "Manam", "Deaths": "", "Country": "Papua New Guinea", "Missing": "", "Longitude": 145.061, "Month": 7, "Injuries": 2, "Location": "New Guinea-NE of", "Volcano Type": "Stratovolcano", "Year": 2015, "Latitude": -4.1, "Type": "Volcanic Activity", "Day": 31, "Damage_Millions_Dollars": "", "VEI": 2}}, {"geometry": {"type": "Point", "coordinates": [98.392, 3.17]}, "type": "Feature", "id": 40, "properties": {"Houses_Destroyed": "", "Elevation": 2460, "Name": "Sinabung", "Deaths": 1, "Country": "Indonesia", "Missing": "", "Longitude": 98.392, "Month": 10, "Injuries": "", "Location": "Sumatra", "Volcano Type": "Stratovolcano", "Year": 2015, "Latitude": 3.17, "Type": "Volcanic Activity", "Day": 16, "Damage_Millions_Dollars": "", "VEI": ""}}, {"geometry": {"type": "Point", "coordinates": [176.5, -38.12]}, "type": "Feature", "id": 41, "properties": {"Houses_Destroyed": "", "Elevation": 1111, "Name": "Okataina", "Deaths": 1, "Country": "New Zealand", "Missing": "", "Longitude": 176.5, "Month": 10, "Injuries": "", "Location": "New Zealand", "Volcano Type": "Lava dome", "Year": 2015, "Latitude": -38.12, "Type": "Volcanic Activity", "Day": "", "Damage_Millions_Dollars": "", "VEI": ""}}, {"geometry": {"type": "Point", "coordinates": [98.392, 3.17]}, "type": "Feature", "id": 42, "properties": {"Houses_Destroyed": "", "Elevation": 2460, "Name": "Sinabung", "Deaths": 1, "Country": "Indonesia", "Missing": "", "Longitude": 98.392, "Month": 5, "Injuries": 4, "Location": "Sumatra", "Volcano Type": "Stratovolcano", "Year": 2016, "Latitude": 3.17, "Type": "Volcanic Activity", "Day": 9, "Damage_Millions_Dollars": "", "VEI": ""}}, {"geometry": {"type": "Point", "coordinates": [98.392, 3.17]}, "type": "Feature", "id": 43, "properties": {"Houses_Destroyed": "", "Elevation": 2460, "Name": "Sinabung", "Deaths": 7, "Country": "Indonesia", "Missing": "", "Longitude": 98.392, "Month": 5, "Injuries": 3, "Location": "Sumatra", "Volcano Type": "Stratovolcano", "Year": 2016, "Latitude": 3.17, "Type": "Volcanic Activity", "Day": 21, "Damage_Millions_Dollars": 100, "VEI": ""}}, {"geometry": {"type": "Point", "coordinates": [-110.67, 44.43]}, "type": "Feature", "id": 44, "properties": {"Houses_Destroyed": "", "Elevation": 2805, "Name": "Yellowstone", "Deaths": 1, "Country": "United States", "Missing": "", "Longitude": -110.67, "Month": 6, "Injuries": "", "Location": "US-Wyoming", "Volcano Type": "Caldera", "Year": 2016, "Latitude": 44.43, "Type": "Volcanic Activity", "Day": 9, "Damage_Millions_Dollars": "", "VEI": ""}}, {"geometry": {"type": "Point", "coordinates": [116.47, -8.42]}, "type": "Feature", "id": 45, "properties": {"Houses_Destroyed": "", "Elevation": 3726, "Name": "Rinjani", "Deaths": "", "Country": "Indonesia", "Missing": 44, "Longitude": 116.47, "Month": 9, "Injuries": "", "Location": "Lesser Sunda Is", "Volcano Type": "Stratovolcano", "Year": 2016, "Latitude": -8.42, "Type": "Volcanic Activity", "Day": 27, "Damage_Millions_Dollars": "", "VEI": ""}}, {"geometry": {"type": "Point", "coordinates": [131.1, 32.88]}, "type": "Feature", "id": 46, "properties": {"Houses_Destroyed": "", "Elevation": 1592, "Name": "Aso", "Deaths": "", "Country": "Japan", "Missing": "", "Longitude": 131.1, "Month": 10, "Injuries": "", "Location": "Kyushu-Japan", "Volcano Type": "Caldera", "Year": 2016, "Latitude": 32.88, "Type": "Volcanic Activity", "Day": 8, "Damage_Millions_Dollars": "", "VEI": ""}}, {"geometry": {"type": "Point", "coordinates": [15.004, 37.734]}, "type": "Feature", "id": 47, "properties": {"Houses_Destroyed": "", "Elevation": 3350, "Name": "Etna", "Deaths": "", "Country": "Italy", "Missing": "", "Longitude": 15.004, "Month": 3, "Injuries": 10, "Location": "Italy", "Volcano Type": "Stratovolcano", "Year": 2017, "Latitude": 37.734, "Type": "Volcanic Activity", "Day": 15, "Damage_Millions_Dollars": "", "VEI": ""}}, {"geometry": {"type": "Point", "coordinates": [98.392, 3.17]}, "type": "Feature", "id": 48, "properties": {"Houses_Destroyed": "", "Elevation": 2460, "Name": "Sinabung", "Deaths": "", "Country": "Indonesia", "Missing": "", "Longitude": 98.392, "Month": 4, "Injuries": "", "Location": "Sumatra", "Volcano Type": "Stratovolcano", "Year": 2017, "Latitude": 3.17, "Type": "Volcanic Activity", "Day": 13, "Damage_Millions_Dollars": "", "VEI": 2}}, {"geometry": {"type": "Point", "coordinates": [-90.88, 14.473]}, "type": "Feature", "id": 49, "properties": {"Houses_Destroyed": "", "Elevation": 3763, "Name": "Fuego", "Deaths": "", "Country": "Guatemala", "Missing": "", "Longitude": -90.88, "Month": 6, "Injuries": "", "Location": "Guatemala", "Volcano Type": "Stratovolcano", "Year": 2017, "Latitude": 14.473, "Type": "Volcanic Activity", "Day": 6, "Damage_Millions_Dollars": "", "VEI": 2}}, {"geometry": {"type": "Point", "coordinates": [109.92, -7.2]}, "type": "Feature", "id": 50, "properties": {"Houses_Destroyed": "", "Elevation": 2565, "Name": "Dieng Volc Complex", "Deaths": 8, "Country": "Indonesia", "Missing": "", "Longitude": 109.92, "Month": 7, "Injuries": 11, "Location": "Java", "Volcano Type": "Complex volcano", "Year": 2017, "Latitude": -7.2, "Type": "Volcanic Activity", "Day": 1, "Damage_Millions_Dollars": "", "VEI": ""}}, {"geometry": {"type": "Point", "coordinates": [14.139, 40.827]}, "type": "Feature", "id": 51, "properties": {"Houses_Destroyed": "", "Elevation": 458, "Name": "Campi Flegrei", "Deaths": 3, "Country": "Italy", "Missing": "", "Longitude": 14.139, "Month": 9, "Injuries": "", "Location": "Italy", "Volcano Type": "Caldera", "Year": 2017, "Latitude": 40.827, "Type": "Volcanic Activity", "Day": 12, "Damage_Millions_Dollars": "", "VEI": ""}}, {"geometry": {"type": "Point", "coordinates": [167.83, -15.4]}, "type": "Feature", "id": 52, "properties": {"Houses_Destroyed": "", "Elevation": 1496, "Name": "Aoba", "Deaths": "", "Country": "Vanuatu", "Missing": "", "Longitude": 167.83, "Month": 9, "Injuries": "", "Location": "Vanuatu-SW Pacific", "Volcano Type": "Shield volcano", "Year": 2017, "Latitude": -15.4, "Type": "Volcanic Activity", "Day": 23, "Damage_Millions_Dollars": "", "VEI": ""}}, {"geometry": {"type": "Point", "coordinates": [110.442, -7.542]}, "type": "Feature", "id": 53, "properties": {"Houses_Destroyed": "", "Elevation": 2947, "Name": "Merapi", "Deaths": 8, "Country": "Indonesia", "Missing": "", "Longitude": 110.442, "Month": 12, "Injuries": 8, "Location": "Java", "Volcano Type": "Stratovolcano", "Year": 2017, "Latitude": -7.542, "Type": "Volcanic Activity", "Day": 18, "Damage_Millions_Dollars": "", "VEI": ""}}, {"geometry": {"type": "Point", "coordinates": [98.392, 3.17]}, "type": "Feature", "id": 54, "properties": {"Houses_Destroyed": "", "Elevation": 2460, "Name": "Sinabung", "Deaths": "", "Country": "Indonesia", "Missing": "", "Longitude": 98.392, "Month": 12, "Injuries": "", "Location": "Sumatra", "Volcano Type": "Stratovolcano", "Year": 2017, "Latitude": 3.17, "Type": "Volcanic Activity", "Day": 27, "Damage_Millions_Dollars": "", "VEI": ""}}, {"geometry": {"type": "Point", "coordinates": [144.62, -3.62]}, "type": "Feature", "id": 55, "properties": {"Houses_Destroyed": "", "Elevation": 365, "Name": "Kadovar", "Deaths": "", "Country": "Papua New Guinea", "Missing": "", "Longitude": 144.62, "Month": 1, "Injuries": "", "Location": "New Guinea-NE of", "Volcano Type": "Stratovolcano", "Year": 2018, "Latitude": -3.62, "Type": "Volcanic Activity", "Day": 5, "Damage_Millions_Dollars": "", "VEI": ""}}, {"geometry": {"type": "Point", "coordinates": [123.685, 13.257]}, "type": "Feature", "id": 56, "properties": {"Houses_Destroyed": "", "Elevation": 2462, "Name": "Mayon", "Deaths": "", "Country": "Philippines", "Missing": "", "Longitude": 123.685, "Month": 1, "Injuries": 1972, "Location": "Luzon-Philippines", "Volcano Type": "Stratovolcano", "Year": 2018, "Latitude": 13.257, "Type": "Volcanic Activity", "Day": 13, "Damage_Millions_Dollars": 3.72, "VEI": ""}}, {"geometry": {"type": "Point", "coordinates": [138.55, 36.62]}, "type": "Feature", "id": 57, "properties": {"Houses_Destroyed": "", "Elevation": 2176, "Name": "Kusatsu-Shirane", "Deaths": 1, "Country": "Japan", "Missing": "", "Longitude": 138.55, "Month": 1, "Injuries": 11, "Location": "Honshu-Japan", "Volcano Type": "Stratovolcano", "Year": 2018, "Latitude": 36.62, "Type": "Volcanic Activity", "Day": 23, "Damage_Millions_Dollars": "", "VEI": ""}}, {"geometry": {"type": "Point", "coordinates": [-155.292, 19.425]}, "type": "Feature", "id": 58, "properties": {"Houses_Destroyed": "", "Elevation": 1222, "Name": "Kilauea", "Deaths": 1, "Country": "United States", "Missing": "", "Longitude": -155.292, "Month": 2, "Injuries": 3, "Location": "Hawaiian Is", "Volcano Type": "Shield volcano", "Year": 2018, "Latitude": 19.425, "Type": "Volcanic Activity", "Day": 1, "Damage_Millions_Dollars": "", "VEI": 1}}, {"geometry": {"type": "Point", "coordinates": [144.62, -3.62]}, "type": "Feature", "id": 59, "properties": {"Houses_Destroyed": "", "Elevation": 365, "Name": "Kadovar", "Deaths": "", "Country": "Papua New Guinea", "Missing": "", "Longitude": 144.62, "Month": 2, "Injuries": "", "Location": "New Guinea-NE of", "Volcano Type": "Stratovolcano", "Year": 2018, "Latitude": -3.62, "Type": "Volcanic Activity", "Day": 9, "Damage_Millions_Dollars": "", "VEI": ""}}, {"geometry": {"type": "Point", "coordinates": [114.242, -8.058]}, "type": "Feature", "id": 60, "properties": {"Houses_Destroyed": "", "Elevation": 2799, "Name": "Ijen", "Deaths": "", "Country": "Indonesia", "Missing": "", "Longitude": 114.242, "Month": 3, "Injuries": 30, "Location": "Java", "Volcano Type": "Stratovolcano", "Year": 2018, "Latitude": -8.058, "Type": "Volcanic Activity", "Day": 21, "Damage_Millions_Dollars": "", "VEI": ""}}, {"geometry": {"type": "Point", "coordinates": [-155.292, 19.425]}, "type": "Feature", "id": 61, "properties": {"Houses_Destroyed": 2, "Elevation": 1222, "Name": "Kilauea", "Deaths": "", "Country": "United States", "Missing": "", "Longitude": -155.292, "Month": 4, "Injuries": "", "Location": "Hawaiian Is", "Volcano Type": "Shield volcano", "Year": 2018, "Latitude": 19.425, "Type": "Volcanic Activity", "Day": 28, "Damage_Millions_Dollars": "", "VEI": 1}}, {"geometry": {"type": "Point", "coordinates": [167.83, -15.4]}, "type": "Feature", "id": 62, "properties": {"Houses_Destroyed": "", "Elevation": 1496, "Name": "Aoba", "Deaths": 4, "Country": "Vanuatu", "Missing": "", "Longitude": 167.83, "Month": 4, "Injuries": "", "Location": "Vanuatu-SW Pacific", "Volcano Type": "Shield volcano", "Year": 2018, "Latitude": -15.4, "Type": "Volcanic Activity", "Day": "", "Damage_Millions_Dollars": "", "VEI": 3}}]}}